unacastclient/__init__.py
unacastclient/address_component.py
unacastclient/catalog.py
unacastclient/client.py
unacastclient/dimension.py
unacastclient/filter.py
unacastclient/index_job.py
unacastclient/layer.py
unacastclient/metric.py
unacastclient/metric_report.py
unacastclient/unacast/__init__.py
unacastclient/unacast/audit/__init__.py
unacastclient/unacast/audit/v1/__init__.py
unacastclient/unacast/catalog/__init__.py
unacastclient/unacast/catalog/v1/__init__.py
unacastclient/unacast/catalog/v2/__init__.py
unacastclient/unacast/catalog/v2/external/__init__.py
unacastclient/unacast/dataset/__init__.py
unacastclient/unacast/dataset/v1/__init__.py
unacastclient/unacast/export/__init__.py
unacastclient/unacast/export/v1/__init__.py
unacastclient/unacast/filter/__init__.py
unacastclient/unacast/filter/v1/__init__.py
unacastclient/unacast/iam/__init__.py
unacastclient/unacast/iam/v1/__init__.py
unacastclient/unacast/index/__init__.py
unacastclient/unacast/index/v1/__init__.py
unacastclient/unacast/lens/__init__.py
unacastclient/unacast/lens/v1/__init__.py
unacastclient/unacast/maps/__init__.py
unacastclient/unacast/maps/v1/__init__.py
unacastclient/unacast/maps/v2/__init__.py
unacastclient/unacast/maps/v2/external/__init__.py
unacastclient/unacast/metric/__init__.py
unacastclient/unacast/metric/v1/__init__.py
unacastclient/unacast/metric/v2/__init__.py
unacastclient/unacast/metric/v2/external/__init__.py
unacastclient/unacast/operator/__init__.py
unacastclient/unacast/operator/v1/__init__.py
unacastclient/unacast/operator/v2/__init__.py
unacastclient/unacast/operator/v2/external/__init__.py
unacastclient/unacast/scorecard/__init__.py
unacastclient/unacast/scorecard/v1/__init__.py
unacastclient/unacast/subscription/__init__.py
unacastclient/unacast/subscription/v1/__init__.py
unacastclient/unacast/subscription/v2/__init__.py
unacastclient/unacast/subscription/v2/external/__init__.py
unacastclient/unacast/unatype/__init__.py
unacastclient/unacast/v2/__init__.py
unacastclient-0.0.58.dist-info/METADATA
unacastclient-0.0.58.dist-info/WHEEL
unacastclient-0.0.58.dist-info/top_level.txt
unacastclient-0.0.58.dist-info/RECORD
