Metadata-Version: 2.1
Name: unacastclient
Version: 0.0.58
Summary: Unacast Python client
Home-page: http://github.com/unacast/unacat
License: MIT
Requires-Dist: grpcio (==1.51.1)
Requires-Dist: grpcio-tools (==1.51.1)
Requires-Dist: grpclib (==0.4.3)
Requires-Dist: pandas (==1.5.2)
Requires-Dist: black (==22.10.0)
Requires-Dist: betterproto[compiler] (==2.0.0b5)
Requires-Dist: syncer (==1.3.0)
Requires-Dist: nest-asyncio (==1.5.6)
Requires-Dist: halo (==0.0.31)
